core_registry_client/__init__.py
core_registry_client/client.py
core_registry_client/models.py
core_registry_client-0.2.0.dist-info/METADATA
core_registry_client-0.2.0.dist-info/WHEEL
core_registry_client-0.2.0.dist-info/RECORD
