Metadata-Version: 2.4
Name: core-registry-client
Version: 0.2.0
Summary: Python client SDK for Schema Registry Service
Author-email: OpenBB <info@openbb.co>
License: MIT
Keywords: client,registry,schema
Requires-Python: >=3.11
Requires-Dist: httpx>=0.26.0
Requires-Dist: jsonschema>=4.21.0
Requires-Dist: pydantic>=2.6.0
Provides-Extra: dev
Requires-Dist: pytest-asyncio>=0.23.3; extra == 'dev'
Requires-Dist: pytest-mock>=3.12.0; extra == 'dev'
Requires-Dist: pytest>=7.4.4; extra == 'dev'
